convert_shp_to_csv/__init__.py
convert_shp_to_csv/main.py
convert_shp_to_csv-0.2.0.dist-info/entry_points.txt
convert_shp_to_csv-0.2.0.dist-info/WHEEL
convert_shp_to_csv-0.2.0.dist-info/METADATA
convert_shp_to_csv-0.2.0.dist-info/RECORD
