Metadata-Version: 2.1
Name: convert-shp-to-csv
Version: 0.2.0
Summary: Converts shape files (.shp) to a gridded csv file
License: MIT
Author: Brandon Rose
Author-email: brandon@jataware.com
Requires-Python: >=3.8,<4.0
Classifier: License :: OSI Approved :: MIT License
Classifier: Programming Language :: Python :: 3
Classifier: Programming Language :: Python :: 3.10
Classifier: Programming Language :: Python :: 3.8
Classifier: Programming Language :: Python :: 3.9
Requires-Dist: Shapely (>=1.8.1,<2.0.0)
Requires-Dist: geopandas (>=0.10.2,<0.11.0)
Requires-Dist: haversine (>=2.5.1,<3.0.0)
Requires-Dist: numpy (>=1.22.3,<2.0.0)
Requires-Dist: pygeos (>=0.12.0,<0.13.0)
